quickbite/.DS_Store
quickbite/.gitignore
quickbite/__init__.py
quickbite/api.py
quickbite/cli.py
quickbite/config.py
quickbite/main.py
quickbite/test_env.py
quickbite-0.1.0.dist-info/LICENSE.rtf
quickbite-0.1.0.dist-info/METADATA
quickbite-0.1.0.dist-info/WHEEL
quickbite-0.1.0.dist-info/RECORD
