Metadata-Version: 2.1
Name: quickbite
Version: 0.1.0
Summary: A command-line tool to generate recipes based on available ingredients.
Author: hafsahshaik
Author-email: hs3373@columbia.edu
Requires-Python: >=3.11,<4.0
Classifier: Programming Language :: Python :: 3
Classifier: Programming Language :: Python :: 3.11
Requires-Dist: python-dotenv (>=1.0.0,<2.0.0)
Requires-Dist: requests (>=2.31.0,<3.0.0)
